lineargebra.py
lineargebra-0.2.dist-info/LICENSE.txt
lineargebra-0.2.dist-info/METADATA
lineargebra-0.2.dist-info/WHEEL
lineargebra-0.2.dist-info/top_level.txt
lineargebra-0.2.dist-info/RECORD
