Metadata-Version: 2.1
Name: lineargebra
Version: 0.2
Summary: A math implementation of Vectors and Matrix
Home-page: UNKNOWN
Author: Thomas Weber
Author-email: thomas.web13@gmail.com
License: UNKNOWN
Platform: UNKNOWN
Classifier: Programming Language :: Python :: 3
Classifier: Programming Language :: Python :: 3.7
Classifier: License :: OSI Approved :: MIT License
